scaife_viewer/__init__.py
scaife_viewer/core/__init__.py
scaife_viewer/core/apps.py
scaife_viewer/core/cli.py
scaife_viewer/core/cloud.py
scaife_viewer/core/conf.py
scaife_viewer/core/hooks.py
scaife_viewer/core/http.py
scaife_viewer/core/indexer.py
scaife_viewer/core/morphology.py
scaife_viewer/core/precomputed.py
scaife_viewer/core/search.py
scaife_viewer/core/urls.py
scaife_viewer/core/utils.py
scaife_viewer/core/views.py
scaife_viewer/core/cts/__init__.py
scaife_viewer/core/cts/capitains.py
scaife_viewer/core/cts/collections.py
scaife_viewer/core/cts/exceptions.py
scaife_viewer/core/cts/heal.py
scaife_viewer/core/cts/passage.py
scaife_viewer/core/cts/reference.py
scaife_viewer/core/cts/resolvers.py
scaife_viewer/core/cts/toc.py
scaife_viewer/core/cts/typing.py
scaife_viewer/core/cts/utils.py
scaife_viewer/core/management/__init__.py
scaife_viewer/core/management/commands/__init__.py
scaife_viewer/core/management/commands/create_index.py
scaife_viewer/core/management/commands/indexer.py
scaife_viewer/core/management/commands/run_reindex_pipeline.py
scaife_viewer/core/templates/search.html
scaife_viewer/core/templates/cts_api/get_passage.xml
scaife_viewer/core/templates/cts_api/get_valid_reffs.xml
scaife_viewer/core/templates/library/base.html
scaife_viewer/core/templates/library/cts_text.html
scaife_viewer/core/templates/library/cts_textgroup.html
scaife_viewer/core/templates/library/cts_work.html
scaife_viewer/core/templates/library/index.html
scaife_viewer/core/templates/reader/reader.html
scaife_viewer/core/tests/__init__.py
scaife_viewer/core/tests/models.py
scaife_viewer/core/tests/settings.py
scaife_viewer/core/tests/tests.py
scaife_viewer/core/tests/urls.py
scaife_viewer_core-0.3rc1.dist-info/LICENSE
scaife_viewer_core-0.3rc1.dist-info/METADATA
scaife_viewer_core-0.3rc1.dist-info/WHEEL
scaife_viewer_core-0.3rc1.dist-info/entry_points.txt
scaife_viewer_core-0.3rc1.dist-info/top_level.txt
scaife_viewer_core-0.3rc1.dist-info/RECORD
